jupyterhubutils/__init__.py
jupyterhubutils/_version.py
jupyterhubutils/singleton.py
jupyterhubutils/authenticator/__init__.py
jupyterhubutils/authenticator/lsstauth.py
jupyterhubutils/authenticator/lsstjwtauth.py
jupyterhubutils/authenticator/lsstjwtloginhandler.py
jupyterhubutils/config/__init__.py
jupyterhubutils/config/lsstconfig.py
jupyterhubutils/loggable/__init__.py
jupyterhubutils/loggable/loggable.py
jupyterhubutils/loggable/loggablechild.py
jupyterhubutils/lsstmgr/__init__.py
jupyterhubutils/lsstmgr/apimanager.py
jupyterhubutils/lsstmgr/envmanager.py
jupyterhubutils/lsstmgr/middlemanager.py
jupyterhubutils/lsstmgr/namespacemanager.py
jupyterhubutils/lsstmgr/optionsformmanager.py
jupyterhubutils/lsstmgr/quotamanager.py
jupyterhubutils/lsstmgr/volumemanager.py
jupyterhubutils/scanrepo/__init__.py
jupyterhubutils/scanrepo/parse_args.py
jupyterhubutils/scanrepo/prepuller.py
jupyterhubutils/scanrepo/prepullerstandalone.py
jupyterhubutils/scanrepo/primerepocache.py
jupyterhubutils/scanrepo/reaper.py
jupyterhubutils/scanrepo/reaperstandalone.py
jupyterhubutils/scanrepo/scanrepo.py
jupyterhubutils/scanrepo/singletonscanner.py
jupyterhubutils/scanrepo/standalone.py
jupyterhubutils/spawner/__init__.py
jupyterhubutils/spawner/lsstspawner.py
jupyterhubutils/spawner/multireflector.py
jupyterhubutils/spawner/multispawner.py
jupyterhubutils/utils/__init__.py
jupyterhubutils/utils/utils.py
jupyterhubutils-0.25.0.dist-info/LICENSE
jupyterhubutils-0.25.0.dist-info/METADATA
jupyterhubutils-0.25.0.dist-info/WHEEL
jupyterhubutils-0.25.0.dist-info/entry_points.txt
jupyterhubutils-0.25.0.dist-info/top_level.txt
jupyterhubutils-0.25.0.dist-info/RECORD
